py_sonora-1.2.8.dist-info/licenses/LICENSE
sonora/__init__.py
sonora/cli.py
sonora/client.py
sonora/events.py
sonora/exceptions.py
sonora/filters.py
sonora/metrics.py
sonora/node.py
sonora/performance.py
sonora/player.py
sonora/py.typed
sonora/queue.py
sonora/security.py
sonora/track.py
sonora/typing.py
sonora/utils.py
sonora/autoplay/__init__.py
sonora/autoplay/engine.py
sonora/autoplay/scorer.py
sonora/autoplay/strategies.py
sonora/diagnostics/__init__.py
sonora/integrations/__init__.py
sonora/integrations/discord_py.py
sonora/plugins/__init__.py
sonora/plugins/youtube.py
sonora/protocol/__init__.py
sonora/queue/__init__.py
sonora/queue/metrics.py
sonora/queue/smart_queue.py
sonora/sdk/__init__.py
sonora/simulator/__init__.py
sonora/snapshot/__init__.py
py_sonora-1.2.8.dist-info/METADATA
py_sonora-1.2.8.dist-info/WHEEL
py_sonora-1.2.8.dist-info/entry_points.txt
py_sonora-1.2.8.dist-info/top_level.txt
py_sonora-1.2.8.dist-info/RECORD
