Metadata-Version: 2.4
Name: py-sonora
Version: 1.2.8
Summary: A full-featured Python Lavalink client for Discord music bots
Author-email: code-xon <ramkrishna@code-xon.fun>
Maintainer-email: Ramkrishna <ramkrishna@code-xon.fun>, Manjunath <manjunathh-dev@code-xon.fun>
License-Expression: MIT
Project-URL: Homepage, https://github.com/code-xon/sonora
Project-URL: Documentation, https://code-xon.github.io/sonora/
Project-URL: Repository, https://github.com/code-xon/sonora
Project-URL: Issues, https://github.com/code-xon/sonora/issues
Project-URL: Changelog, https://github.com/code-xon/sonora/blob/main/CHANGELOG.md
Keywords: discord,lavalink,music,audio,bot,sonora,code-xon
Classifier: Development Status :: 5 - Production/Stable
Classifier: Intended Audience :: Developers
Classifier: Operating System :: OS Independent
Classifier: Programming Language :: Python :: 3
Classifier: Programming Language :: Python :: 3.11
Classifier: Programming Language :: Python :: 3.12
Classifier: Programming Language :: Python :: 3.13
Classifier: Topic :: Multimedia :: Sound/Audio :: Players
Classifier: Topic :: Software Development :: Libraries :: Python Modules
Requires-Python: >=3.11
License-File: LICENSE
Requires-Dist: aiohttp>=3.8.0
Requires-Dist: pydantic>=2.0.0
Requires-Dist: typing-extensions>=4.0.0
Provides-Extra: dev
Requires-Dist: pytest>=7.0.0; extra == "dev"
Requires-Dist: pytest-asyncio>=0.21.0; extra == "dev"
Requires-Dist: pytest-cov>=4.0.0; extra == "dev"
Requires-Dist: black>=23.0.0; extra == "dev"
Requires-Dist: ruff>=0.1.0; extra == "dev"
Requires-Dist: mypy>=1.0.0; extra == "dev"
Requires-Dist: pre-commit>=3.0.0; extra == "dev"
Requires-Dist: mkdocs>=1.4.0; extra == "dev"
Requires-Dist: mkdocstrings[python]>=0.20.0; extra == "dev"
Provides-Extra: discord
Requires-Dist: discord.py>=2.0.0; extra == "discord"
Provides-Extra: pycord
Requires-Dist: py-cord>=2.0.0; extra == "pycord"
Provides-Extra: nextcord
Requires-Dist: nextcord>=2.0.0; extra == "nextcord"
Dynamic: license-file
